python_alpaca_server/__init__.py
python_alpaca_server/__main__.py
python_alpaca_server/api/__init__.py
python_alpaca_server/api/common.py
python_alpaca_server/api/covercalibrator.py
python_alpaca_server/api/dome.py
python_alpaca_server/api/filterwheel.py
python_alpaca_server/api/focuser.py
python_alpaca_server/api/management.py
python_alpaca_server/api/observingconditions.py
python_alpaca_server/api/rotator.py
python_alpaca_server/api/safetymonitor.py
python_alpaca_server/api/switch.py
python_alpaca_server/app.py
python_alpaca_server/device.py
python_alpaca_server/devices/__init__.py
python_alpaca_server/devices/camera.py
python_alpaca_server/devices/covercalibrator.py
python_alpaca_server/devices/dome.py
python_alpaca_server/devices/filterwheel.py
python_alpaca_server/devices/focuser.py
python_alpaca_server/devices/observingconditions.py
python_alpaca_server/devices/rotator.py
python_alpaca_server/devices/safetymonitor.py
python_alpaca_server/devices/switch.py
python_alpaca_server/devices/telescope.py
python_alpaca_server/discovery.py
python_alpaca_server/errors.py
python_alpaca_server/middleware.py
python_alpaca_server/request.py
python_alpaca_server/response.py
python_alpaca_server-2.0.0.dist-info/LICENSE
python_alpaca_server-2.0.0.dist-info/METADATA
python_alpaca_server-2.0.0.dist-info/WHEEL
python_alpaca_server-2.0.0.dist-info/RECORD
