Metadata-Version: 2.1
Name: python-alpaca-server
Version: 2.0.0
Summary: An http ASCOM Alpaca server written in python.
License: Apache-2.0
Author: Rick Bassham
Author-email: rick@darkdragonsastro.com
Requires-Python: >=3.8.1,<4
Classifier: License :: OSI Approved :: Apache Software License
Classifier: Programming Language :: Python :: 3
Classifier: Programming Language :: Python :: 3.9
Classifier: Programming Language :: Python :: 3.10
Classifier: Programming Language :: Python :: 3.11
Requires-Dist: asyncudp (>=0.11.0,<0.12.0)
Requires-Dist: fastapi-utils (>=0.7.0,<0.8.0)
Requires-Dist: fastapi[standard] (>=0.115.0,<0.116.0)
Requires-Dist: python-multipart (>=0.0.9,<0.0.10)
Requires-Dist: structlog (>=24.4.0,<25.0.0)
Requires-Dist: watchfiles (>=0.24.0,<0.25.0)
